MisrToolkit/MisrToolkit.cpython-36m-darwin.so
MisrToolkit/__init__.py
MisrToolkit-1.5.1.dist-info/METADATA
MisrToolkit-1.5.1.dist-info/WHEEL
MisrToolkit-1.5.1.dist-info/top_level.txt
MisrToolkit-1.5.1.dist-info/RECORD
