Metadata-Version: 2.1
Name: MisrToolkit
Version: 1.5.1
Summary: Python interface to MISR Toolkit
Home-page: https://github.com/nasa/Misr-Toolkit
Author: MISR Project
Author-email: UNKNOWN
License: BSD-3-Clause
Platform: UNKNOWN
